ptodnes/DNS/__init__.py
ptodnes/DNS/dns_record_dict.py
ptodnes/DNS/odnesdns.py
ptodnes/DNS/record.py
ptodnes/__init__.py
ptodnes/__main__.py
ptodnes/configprovider/__init__.py
ptodnes/configprovider/configprovider.py
ptodnes/dataexporter/__init__.py
ptodnes/datasources/__init__.py
ptodnes/datasources/crtsh.py
ptodnes/datasources/datasource.py
ptodnes/datasources/securitytrails.py
ptodnes/datasources/shodan.py
ptodnes/datasources/virustotal.py
ptodnes/datasources/wordlist.py
ptodnes/metaclasses/__init__.py
ptodnes/process.py
ptodnes/ptodnes.py
ptodnes-1.11.2.4.dist-info/METADATA
ptodnes-1.11.2.4.dist-info/WHEEL
ptodnes-1.11.2.4.dist-info/entry_points.txt
ptodnes-1.11.2.4.dist-info/RECORD
