Metadata-Version: 2.4
Name: ptodnes
Version: 1.11.2.4
Summary: 
License: MIT
Author: Ondrej Dohnal
Author-email: xdohna45@vutbr.cz
Requires-Python: >3.11,<=3.15
Classifier: License :: OSI Approved :: MIT License
Classifier: Programming Language :: Python :: 3
Classifier: Programming Language :: Python :: 3.12
Classifier: Programming Language :: Python :: 3.13
Classifier: Programming Language :: Python :: 3.14
Requires-Dist: aiodns (>=3.2.0,<4.0.0)
Requires-Dist: aiofiles (>=25.1.0,<26.0.0)
Requires-Dist: aiohttp (>=3.11.13,<4.0.0)
Requires-Dist: aiopg (>=1.4.0,<2.0.0)
Requires-Dist: ptlibs (>=1.0.17,<2.0.0)
Requires-Dist: punycode (>=0.2.1,<0.3.0)
Requires-Dist: pyyaml (>=6.0.2,<7.0.0)
